AUTHORS
CHANGELOG
LICENSE
MANIFEST.in
NOTICE
README
README.rst
run-tests.py
setup.py
Kaylee.egg-info/PKG-INFO
Kaylee.egg-info/SOURCES.txt
Kaylee.egg-info/dependency_links.txt
Kaylee.egg-info/not-zip-safe
Kaylee.egg-info/requires.txt
Kaylee.egg-info/top_level.txt
kaylee/__init__.py
kaylee/controller.py
kaylee/core.py
kaylee/errors.py
kaylee/loader.py
kaylee/node.py
kaylee/project.py
kaylee/server.py
kaylee/session.py
kaylee/storage.py
kaylee/util.py
kaylee/bin/kaylee-admin.py
kaylee/client/.gitignore
kaylee/client/Makefile
kaylee/client/kaylee.coffee
kaylee/client/kaylee.js
kaylee/client/klajax.coffee
kaylee/client/klbenchmark.coffee
kaylee/client/klshared.coffee
kaylee/client/klutil.coffee
kaylee/client/klworker.coffee
kaylee/client/klworker.js
kaylee/contrib/__init__.py
kaylee/contrib/controllers.py
kaylee/contrib/registries.py
kaylee/contrib/storages.py
kaylee/contrib/frontends/__init__.py
kaylee/contrib/frontends/django_frontend/__init__.py
kaylee/contrib/frontends/django_frontend/models.py
kaylee/contrib/frontends/django_frontend/tests.py
kaylee/contrib/frontends/django_frontend/urls.py
kaylee/contrib/frontends/django_frontend/views.py
kaylee/contrib/frontends/flask_frontend/__init__.py
kaylee/contrib/frontends/flask_frontend/flask_frontend.py
kaylee/contrib/frontends/werkzeug_frontend/__init__.py
kaylee/contrib/frontends/werkzeug_frontend/werkzeug_frontend.py
kaylee/manager/__init__.py
kaylee/manager/command.py
kaylee/manager/commands/__init__.py
kaylee/manager/commands/build.py
kaylee/manager/commands/run.py
kaylee/manager/commands/start_env.py
kaylee/manager/commands/start_project.py
kaylee/manager/commands/templates/build_template/index.html
kaylee/manager/commands/templates/build_template/css/klconsole.css
kaylee/manager/commands/templates/build_template/js/.gitignore
kaylee/manager/commands/templates/build_template/js/Makefile
kaylee/manager/commands/templates/build_template/js/jquery.min.js
kaylee/manager/commands/templates/build_template/js/klconsole.coffee
kaylee/manager/commands/templates/build_template/js/kldebug.coffee
kaylee/manager/commands/templates/build_template/js/kldebug.js
